cdk_pynamodb/__init__.py
cdk_pynamodb/cdk_pynamodb.py
cdk_pynamodb-0.1.1.dist-info/LICENSE
cdk_pynamodb-0.1.1.dist-info/WHEEL
cdk_pynamodb-0.1.1.dist-info/METADATA
cdk_pynamodb-0.1.1.dist-info/RECORD
