Metadata-Version: 2.1
Name: cdk-pynamodb
Version: 0.1.1
Summary: AWS CDK DynamoDB table construct from PynamoDB models.
Home-page: https://github.com/altoria/cdk-pynamodb
License: MIT
Author: SeongHun Kim
Author-email: alto@pendragon.kr
Requires-Python: >=3.7,<4.0
Classifier: License :: OSI Approved :: MIT License
Classifier: Programming Language :: Python :: 3
Classifier: Programming Language :: Python :: 3.7
Classifier: Programming Language :: Python :: 3.8
Classifier: Programming Language :: Python :: 3.9
Classifier: Programming Language :: Python :: 3.10
Classifier: Programming Language :: Python :: 3.11
Requires-Dist: aws-cdk-lib (>=2.60.0,<3.0.0)
Requires-Dist: pynamodb (>=5.3.4,<6.0.0)
